restack_toolhouse/__init__.py
restack_toolhouse/functions/send_email.py
restack_toolhouse/functions/summarize_website.py
restack_toolhouse/service.py
restack_toolhouse/task_queue.py
restack_toolhouse/utils/toolhouse_client.py
restack_toolhouse-0.0.13.dist-info/METADATA
restack_toolhouse-0.0.13.dist-info/WHEEL
restack_toolhouse-0.0.13.dist-info/RECORD
