Metadata-Version: 2.1
Name: restack_toolhouse
Version: 0.0.13
Summary: Toolhouse for Restack AI
Author: Restack Team
Author-email: service@restack.io
Requires-Python: >=3.9,<4.0
Classifier: Programming Language :: Python :: 3
Classifier: Programming Language :: Python :: 3.9
Classifier: Programming Language :: Python :: 3.10
Classifier: Programming Language :: Python :: 3.11
Classifier: Programming Language :: Python :: 3.12
Classifier: Programming Language :: Python :: 3.13
Requires-Dist: pydantic (>=2.9.2,<3.0.0)
Requires-Dist: restack_ai (>=0.0.28,<0.0.29)
Requires-Dist: toolhouse (>=1.3.0,<2.0.0)
